{
    "categories": [
        {
            "id": 1,
            "name": "공간_다목적공간"
        },
        {
            "id": 2,
            "name": "공간_엘리베이터홀"
        },
        {
            "id": 3,
            "name": "공간_계단실"
        },
        {
            "id": 4,
            "name": "객체_변기"
        },
        {
            "id": 5,
            "name": "객체_세면대"
        },
        {
            "id": 6,
            "name": "객체_싱크대"
        },
        {
            "id": 7,
            "name": "객체_욕조"
        },
        {
            "id": 8,
            "name": "객체_가스레인지"
        },
        {
            "id": 9,
            "name": "구조_출입문"
        },
        {
            "id": 10,
            "name": "구조_창호"
        },
        {
            "id": 11,
            "name": "구조_벽체"
        },
        {
            "id": 13,
            "name": "공간_거실"
        },
        {
            "id": 14,
            "name": "공간_침실"
        },
        {
            "id": 15,
            "name": "공간_주방"
        },
        {
            "id": 16,
            "name": "공간_현관"
        },
        {
            "id": 17,
            "name": "공간_발코니"
        },
        {
            "id": 18,
            "name": "공간_화장실"
        },
        {
            "id": 19,
            "name": "공간_실외기실"
        },
        {
            "id": 20,
            "name": "공간_드레스룸"
        },
        {
            "id": 21,
            "name": "OCR"
        },
        {
            "id": 22,
            "name": "공간_기타"
        },
        {
            "id": 23,
            "name": "공간_엘리베이터"
        }
    ],
    "images": [
        {
            "id": 3,
            "width": 4963,
            "height": 3508,
            "file_name": "APT_FP_SPA_286216738.png"
        }
    ],
    "annotations": [
        {
            "id": 22,
            "image_id": 3,
            "category_id": 15,
            "segmentation": [
                [
                    1826.8,
                    1714.2,
                    2150.2,
                    1713.7,
                    2150.9,
                    1815.3,
                    2171.7,
                    1818.6,
                    2171.3,
                    1696.6,
                    2277.4,
                    1692.4,
                    2277.0,
                    1713.8,
                    2422.2,
                    1712.4,
                    2419.29,
                    2410.74,
                    2086.7,
                    2411.91,
                    2086.7,
                    2240.93,
                    2064.45,
                    2240.93,
                    2066.0,
                    2411.1,
                    1809.4,
                    2409.7,
                    1808.1,
                    1815.9,
                    1827.5,
                    1815.3
                ]
            ],
            "area": 420967.0,
            "bbox": [
                1808.1,
                1692.4,
                614.1,
                719.51
            ],
            "iscrowd": 0,
            "attributes": {
                "occluded": false
            }
        },
        {
            "id": 23,
            "image_id": 3,
            "category_id": 1,
            "segmentation": [
                [
                    3306.7,
                    1199.6,
                    3515.3,
                    1200.4,
                    3516.4,
                    1504.0,
                    3305.6,
                    1501.4
                ]
            ],
            "area": 63467.0,
            "bbox": [
                3305.6,
                1199.6,
                210.8,
                304.4
            ],
            "iscrowd": 0,
            "attributes": {
                "occluded": false
            }
        },
        {
            "id": 24,
            "image_id": 3,
            "category_id": 13,
            "segmentation": [
                [
                    1092.87,
                    1520.51,
                    3488.56,
                    1519.15,
                    3489.24,
                    1694.0,
                    1807.17,
                    1694.0,
                    1809.4,
                    2409.7,
                    1090.84,
                    2415.08
                ]
            ],
            "area": 932171.0,
            "bbox": [
                1090.84,
                1519.15,
                2398.4,
                895.93
            ],
            "iscrowd": 0,
            "attributes": {
                "occluded": false
            }
        },
        {
            "id": 25,
            "image_id": 3,
            "category_id": 16,
            "segmentation": [
                [
                    2427.5,
                    1200.9,
                    2802.1,
                    1199.6,
                    2801.7,
                    1320.5,
                    2675.3,
                    1319.9,
                    2675.5,
                    1312.5,
                    2656.7,
                    1313.0,
                    2657.4,
                    1366.9,
                    2674.9,
                    1366.0,
                    2675.7,
                    1338.9,
                    2718.0,
                    1338.1,
                    2716.9,
                    1502.5,
                    2675.2,
                    1501.7,
                    2674.8,
                    1477.7,
                    2655.8,
                    1478.3,
                    2655.8,
                    1519.0,
                    2478.78,
                    1520.07,
                    2478.45,
                    1501.11,
                    2328.77,
                    1502.42,
                    2328.9,
                    1410.6,
                    2427.1,
                    1409.6
                ]
            ],
            "area": 107557.0,
            "bbox": [
                2328.77,
                1199.6,
                473.33,
                320.47
            ],
            "iscrowd": 0,
            "attributes": {
                "occluded": false
            }
        },
        {
            "id": 26,
            "image_id": 3,
            "category_id": 18,
            "segmentation": [
                [
                    1839.86,
                    847.3,
                    1988.57,
                    847.77,
                    1989.04,
                    940.48,
                    2210.24,
                    940.48,
                    2213.53,
                    1244.98,
                    1837.97,
                    1243.1
                ]
            ],
            "area": 127279.0,
            "bbox": [
                1837.97,
                847.3,
                375.56,
                397.68
            ],
            "iscrowd": 0,
            "attributes": {
                "occluded": false
            }
        },
        {
            "id": 27,
            "image_id": 3,
            "category_id": 14,
            "segmentation": [
                [
                    3347.2,
                    1713.1,
                    3849.4,
                    1712.9,
                    3850.4,
                    2411.9,
                    3346.0,
                    2410.0
                ]
            ],
            "area": 351315.0,
            "bbox": [
                3346.0,
                1712.9,
                504.4,
                699.0
            ],
            "iscrowd": 0,
            "attributes": {
                "occluded": false
            }
        },
        {
            "id": 28,
            "image_id": 3,
            "category_id": 17,
            "segmentation": [
                [
                    2921.0,
                    2244.7,
                    3326.7,
                    2243.0,
                    3327.3,
                    2413.8,
                    2921.9,
                    2411.2
                ]
            ],
            "area": 68370.0,
            "bbox": [
                2921.0,
                2243.0,
                406.3,
                170.8
            ],
            "iscrowd": 0,
            "attributes": {
                "occluded": false
            }
        },
        {
            "id": 29,
            "image_id": 3,
            "category_id": 18,
            "segmentation": [
                [
                    3125.6,
                    1198.9,
                    3287.8,
                    1198.3,
                    3288.8,
                    1502.1,
                    2967.4,
                    1502.6,
                    2967.86,
                    1325.68,
                    3125.2,
                    1326.8
                ]
            ],
            "area": 77193.0,
            "bbox": [
                2967.4,
                1198.3,
                321.4,
                304.3
            ],
            "iscrowd": 0,
            "attributes": {
                "occluded": false
            }
        },
        {
            "id": 30,
            "image_id": 3,
            "category_id": 22,
            "segmentation": [
                [
                    3535.2,
                    1198.52,
                    3625.4,
                    1198.5,
                    3627.69,
                    1314.54,
                    3535.2,
                    1314.2
                ]
            ],
            "area": 10546.0,
            "bbox": [
                3535.2,
                1198.5,
                92.49,
                116.04
            ],
            "iscrowd": 0,
            "attributes": {
                "occluded": false
            }
        },
        {
            "id": 31,
            "image_id": 3,
            "category_id": 22,
            "segmentation": [
                [
                    2968.7,
                    1197.9,
                    3106.3,
                    1200.3,
                    3107.9,
                    1306.6,
                    2968.6,
                    1307.4
                ]
            ],
            "area": 14908.0,
            "bbox": [
                2968.6,
                1197.9,
                139.3,
                109.5
            ],
            "iscrowd": 0,
            "attributes": {
                "occluded": false
            }
        },
        {
            "id": 32,
            "image_id": 3,
            "category_id": 14,
            "segmentation": [
                [
                    2920.9,
                    1713.0,
                    3325.9,
                    1711.3,
                    3326.9,
                    2224.7,
                    2920.5,
                    2222.9
                ]
            ],
            "area": 207470.0,
            "bbox": [
                2920.5,
                1711.3,
                406.4,
                513.4
            ],
            "iscrowd": 0,
            "attributes": {
                "occluded": false
            }
        },
        {
            "id": 33,
            "image_id": 3,
            "category_id": 22,
            "segmentation": [
                [
                    2441.2,
                    1712.2,
                    2517.4,
                    1711.5,
                    2519.5,
                    1845.0,
                    2441.0,
                    1841.8
                ]
            ],
            "area": 10183.0,
            "bbox": [
                2441.0,
                1711.5,
                78.5,
                133.5
            ],
            "iscrowd": 0,
            "attributes": {
                "occluded": false
            }
        },
        {
            "id": 34,
            "image_id": 3,
            "category_id": 20,
            "segmentation": [
                [
                    3507.7,
                    1521.4,
                    3852.0,
                    1521.4,
                    3852.8,
                    1695.5,
                    3506.6,
                    1694.8
                ]
            ],
            "area": 60094.0,
            "bbox": [
                3506.6,
                1521.4,
                346.2,
                174.1
            ],
            "iscrowd": 0,
            "attributes": {
                "occluded": false
            }
        },
        {
            "id": 35,
            "image_id": 3,
            "category_id": 18,
            "segmentation": [
                [
                    3644.0,
                    1199.8,
                    3850.7,
                    1200.3,
                    3850.5,
                    1502.8,
                    3535.86,
                    1503.11,
                    3535.5,
                    1333.1,
                    3643.3,
                    1332.9
                ]
            ],
            "area": 81103.0,
            "bbox": [
                3535.5,
                1199.8,
                315.2,
                303.31
            ],
            "iscrowd": 0,
            "attributes": {
                "occluded": false
            }
        },
        {
            "id": 36,
            "image_id": 3,
            "category_id": 14,
            "segmentation": [
                [
                    1091.8,
                    846.5,
                    1816.9,
                    847.8,
                    1818.4,
                    1501.4,
                    1092.9,
                    1500.9
                ]
            ],
            "area": 474116.0,
            "bbox": [
                1091.8,
                846.5,
                726.6,
                654.9
            ],
            "iscrowd": 0,
            "attributes": {
                "occluded": false
            }
        },
        {
            "id": 37,
            "image_id": 3,
            "category_id": 14,
            "segmentation": [
                [
                    2544.12,
                    1716.64,
                    2897.3,
                    1713.6,
                    2899.9,
                    2411.2,
                    2442.1,
                    2410.7,
                    2442.24,
                    1867.21,
                    2545.03,
                    1866.81
                ]
            ],
            "area": 302253.0,
            "bbox": [
                2442.1,
                1713.6,
                457.8,
                697.6
            ],
            "iscrowd": 0,
            "attributes": {
                "occluded": false
            }
        },
        {
            "id": 38,
            "image_id": 3,
            "category_id": 20,
            "segmentation": [
                [
                    1818.5,
                    1266.1,
                    2232.36,
                    1265.17,
                    2231.89,
                    1201.17,
                    2310.01,
                    1199.28,
                    2310.48,
                    1272.23,
                    2408.85,
                    1274.11,
                    2410.26,
                    1392.24,
                    2308.6,
                    1391.3,
                    2309.26,
                    1501.19,
                    1839.1,
                    1502.13,
                    1838.16,
                    1376.95,
                    1818.4,
                    1377.4
                ]
            ],
            "area": 130282.0,
            "bbox": [
                1818.4,
                1199.28,
                591.86,
                302.85
            ],
            "iscrowd": 0,
            "attributes": {
                "occluded": false
            }
        },
        {
            "id": 39,
            "image_id": 3,
            "category_id": 22,
            "segmentation": [
                [
                    2820.9,
                    1198.2,
                    2949.4,
                    1199.5,
                    2949.4,
                    1503.3,
                    2737.8,
                    1501.1,
                    2736.26,
                    1340.25,
                    2822.22,
                    1339.93
                ]
            ],
            "area": 52384.0,
            "bbox": [
                2736.26,
                1198.2,
                213.14,
                305.1
            ],
            "iscrowd": 0,
            "attributes": {
                "occluded": false
            }
        },
        {
            "id": 40,
            "image_id": 3,
            "category_id": 22,
            "segmentation": [
                [
                    2329.18,
                    1199.34,
                    2409.75,
                    1198.39,
                    2410.34,
                    1253.21,
                    2327.86,
                    1254.0
                ]
            ],
            "area": 4459.0,
            "bbox": [
                2327.86,
                1198.39,
                82.48,
                55.61
            ],
            "iscrowd": 0,
            "attributes": {
                "occluded": false
            }
        },
        {
            "id": 41,
            "image_id": 3,
            "category_id": 22,
            "segmentation": [
                [
                    2006.72,
                    848.59,
                    2212.95,
                    845.65,
                    2213.6,
                    925.39,
                    2006.4,
                    926.05
                ]
            ],
            "area": 16252.0,
            "bbox": [
                2006.4,
                845.65,
                207.2,
                80.4
            ],
            "iscrowd": 0,
            "attributes": {
                "occluded": false
            }
        }
    ]
}