{
    "categories": [
        {
            "id": 1,
            "name": "공간_다목적공간"
        },
        {
            "id": 2,
            "name": "공간_엘리베이터홀"
        },
        {
            "id": 3,
            "name": "공간_계단실"
        },
        {
            "id": 4,
            "name": "객체_변기"
        },
        {
            "id": 5,
            "name": "객체_세면대"
        },
        {
            "id": 6,
            "name": "객체_싱크대"
        },
        {
            "id": 7,
            "name": "객체_욕조"
        },
        {
            "id": 8,
            "name": "객체_가스레인지"
        },
        {
            "id": 9,
            "name": "구조_출입문"
        },
        {
            "id": 10,
            "name": "구조_창호"
        },
        {
            "id": 11,
            "name": "구조_벽체"
        },
        {
            "id": 13,
            "name": "공간_거실"
        },
        {
            "id": 14,
            "name": "공간_침실"
        },
        {
            "id": 15,
            "name": "공간_주방"
        },
        {
            "id": 16,
            "name": "공간_현관"
        },
        {
            "id": 17,
            "name": "공간_발코니"
        },
        {
            "id": 18,
            "name": "공간_화장실"
        },
        {
            "id": 19,
            "name": "공간_실외기실"
        },
        {
            "id": 20,
            "name": "공간_드레스룸"
        },
        {
            "id": 21,
            "name": "OCR"
        },
        {
            "id": 22,
            "name": "공간_기타"
        },
        {
            "id": 23,
            "name": "공간_엘리베이터"
        }
    ],
    "images": [
        {
            "id": 3,
            "width": 4961,
            "height": 3508,
            "file_name": "APT_FP_SPA_218608466.png"
        }
    ],
    "annotations": [
        {
            "id": 42,
            "image_id": 3,
            "category_id": 23,
            "segmentation": [
                [
                    1656.59,
                    1683.7,
                    1943.97,
                    1683.43,
                    1944.5,
                    1972.03,
                    1657.11,
                    1971.54
                ]
            ],
            "area": 82776.0,
            "bbox": [
                1656.59,
                1683.43,
                287.91,
                288.6
            ],
            "iscrowd": 0,
            "attributes": {
                "occluded": false
            }
        },
        {
            "id": 43,
            "image_id": 3,
            "category_id": 22,
            "segmentation": [
                [
                    2895.96,
                    1194.49,
                    3064.42,
                    1194.84,
                    3064.38,
                    1326.41,
                    2896.21,
                    1327.22
                ]
            ],
            "area": 22197.0,
            "bbox": [
                2895.96,
                1194.49,
                168.46,
                132.73
            ],
            "iscrowd": 0,
            "attributes": {
                "occluded": false
            }
        },
        {
            "id": 44,
            "image_id": 3,
            "category_id": 22,
            "segmentation": [
                [
                    2359.01,
                    2268.8,
                    2405.71,
                    2268.9,
                    2405.51,
                    2309.5,
                    2359.31,
                    2309.5
                ]
            ],
            "area": 1927.0,
            "bbox": [
                2359.01,
                2268.8,
                46.7,
                40.7
            ],
            "iscrowd": 0,
            "attributes": {
                "occluded": false
            }
        },
        {
            "id": 45,
            "image_id": 3,
            "category_id": 17,
            "segmentation": [
                [
                    2707.1,
                    2177.8,
                    2975.09,
                    2178.16,
                    2975.17,
                    2187.12,
                    3064.15,
                    2186.95,
                    3064.56,
                    2311.99,
                    2706.49,
                    2312.26
                ]
            ],
            "area": 47085.0,
            "bbox": [
                2706.49,
                2177.8,
                358.07,
                134.46
            ],
            "iscrowd": 0,
            "attributes": {
                "occluded": false
            }
        },
        {
            "id": 46,
            "image_id": 3,
            "category_id": 14,
            "segmentation": [
                [
                    2686.13,
                    1360.95,
                    2881.8,
                    1360.92,
                    2881.8,
                    1351.54,
                    3064.21,
                    1351.87,
                    3064.45,
                    1693.14,
                    2685.5,
                    1694.01
                ]
            ],
            "area": 127370.0,
            "bbox": [
                2685.5,
                1351.54,
                378.95,
                342.47
            ],
            "iscrowd": 0,
            "attributes": {
                "occluded": false
            }
        },
        {
            "id": 47,
            "image_id": 3,
            "category_id": 22,
            "segmentation": [
                [
                    3027.59,
                    1716.5,
                    3064.15,
                    1716.62,
                    3064.59,
                    1867.2,
                    3027.63,
                    1867.08
                ]
            ],
            "area": 5438.0,
            "bbox": [
                3027.59,
                1716.5,
                37.0,
                150.7
            ],
            "iscrowd": 0,
            "attributes": {
                "occluded": false
            }
        },
        {
            "id": 48,
            "image_id": 3,
            "category_id": 18,
            "segmentation": [
                [
                    2832.51,
                    1716.59,
                    3016.64,
                    1716.32,
                    3016.52,
                    1866.86,
                    2832.53,
                    1866.84
                ]
            ],
            "area": 27692.0,
            "bbox": [
                2832.51,
                1716.32,
                184.13,
                150.54
            ],
            "iscrowd": 0,
            "attributes": {
                "occluded": false
            }
        },
        {
            "id": 49,
            "image_id": 3,
            "category_id": 14,
            "segmentation": [
                [
                    2706.27,
                    1889.79,
                    3064.13,
                    1890.48,
                    3064.65,
                    2172.66,
                    3056.01,
                    2172.66,
                    3055.84,
                    2156.59,
                    2707.82,
                    2156.76
                ]
            ],
            "area": 95518.0,
            "bbox": [
                2706.27,
                1889.79,
                358.38,
                282.87
            ],
            "iscrowd": 0,
            "attributes": {
                "occluded": false
            }
        },
        {
            "id": 50,
            "image_id": 3,
            "category_id": 22,
            "segmentation": [
                [
                    2580.7,
                    2285.6,
                    2694.9,
                    2285.66,
                    2694.9,
                    2310.1,
                    2580.67,
                    2309.65
                ]
            ],
            "area": 2736.0,
            "bbox": [
                2580.67,
                2285.6,
                114.23,
                24.5
            ],
            "iscrowd": 0,
            "attributes": {
                "occluded": false
            }
        },
        {
            "id": 51,
            "image_id": 3,
            "category_id": 17,
            "segmentation": [
                [
                    2356.14,
                    2142.43,
                    2435.86,
                    2142.81,
                    2435.86,
                    2128.71,
                    2583.03,
                    2128.38,
                    2582.9,
                    2145.41,
                    2670.74,
                    2145.4,
                    2671.16,
                    2189.36,
                    2693.77,
                    2189.77,
                    2694.2,
                    2274.1,
                    2568.8,
                    2274.16,
                    2569.0,
                    2312.11,
                    2418.32,
                    2311.58,
                    2418.27,
                    2257.65,
                    2356.4,
                    2257.45
                ]
            ],
            "area": 49857.0,
            "bbox": [
                2356.14,
                2128.38,
                338.06,
                183.73
            ],
            "iscrowd": 0,
            "attributes": {
                "occluded": false
            }
        },
        {
            "id": 52,
            "image_id": 3,
            "category_id": 15,
            "segmentation": [
                [
                    2355.62,
                    1810.06,
                    2356.24,
                    2112.18,
                    2583.51,
                    2111.97,
                    2583.51,
                    2121.51,
                    2685.11,
                    2121.3,
                    2685.1,
                    1810.6
                ]
            ],
            "area": 100262.0,
            "bbox": [
                2355.62,
                1810.06,
                329.49,
                311.45
            ],
            "iscrowd": 0,
            "attributes": {
                "occluded": false
            }
        },
        {
            "id": 53,
            "image_id": 3,
            "category_id": 13,
            "segmentation": [
                [
                    2296.58,
                    1360.27,
                    2664.3,
                    1360.54,
                    2663.82,
                    1716.29,
                    2820.02,
                    1716.72,
                    2820.5,
                    1866.9,
                    2685.26,
                    1867.31,
                    2685.1,
                    1810.6,
                    2162.36,
                    1809.83,
                    2162.26,
                    1683.05,
                    2296.65,
                    1683.03
                ]
            ],
            "area": 204575.0,
            "bbox": [
                2162.26,
                1360.27,
                658.24,
                507.04
            ],
            "iscrowd": 0,
            "attributes": {
                "occluded": false
            }
        },
        {
            "id": 54,
            "image_id": 3,
            "category_id": 22,
            "segmentation": [
                [
                    1967.72,
                    1922.62,
                    2151.92,
                    1923.48,
                    2151.92,
                    1972.38,
                    1967.72,
                    1972.04
                ]
            ],
            "area": 9016.0,
            "bbox": [
                1967.72,
                1922.62,
                184.2,
                49.76
            ],
            "iscrowd": 0,
            "attributes": {
                "occluded": false
            }
        },
        {
            "id": 55,
            "image_id": 3,
            "category_id": 18,
            "segmentation": [
                [
                    1978.9,
                    1683.72,
                    2151.7,
                    1683.29,
                    2152.08,
                    1912.44,
                    1978.38,
                    1911.26
                ]
            ],
            "area": 39526.0,
            "bbox": [
                1978.38,
                1683.29,
                173.7,
                229.15
            ],
            "iscrowd": 0,
            "attributes": {
                "occluded": false
            }
        },
        {
            "id": 56,
            "image_id": 3,
            "category_id": 16,
            "segmentation": [
                [
                    2162.36,
                    1809.83,
                    2287.19,
                    1810.24,
                    2287.29,
                    1823.12,
                    2333.81,
                    1822.97,
                    2335.53,
                    1972.92,
                    2284.14,
                    1973.1,
                    2284.18,
                    1978.35,
                    2167.21,
                    1977.48,
                    2167.21,
                    1972.13,
                    2162.71,
                    1971.96
                ]
            ],
            "area": 27971.0,
            "bbox": [
                2162.36,
                1809.83,
                173.17,
                168.52
            ],
            "iscrowd": 0,
            "attributes": {
                "occluded": false
            }
        },
        {
            "id": 57,
            "image_id": 3,
            "category_id": 22,
            "segmentation": [
                [
                    2290.27,
                    1995.04,
                    2333.57,
                    1995.24,
                    2333.62,
                    2138.3,
                    2290.52,
                    2138.1
                ]
            ],
            "area": 6256.0,
            "bbox": [
                2290.27,
                1995.04,
                43.35,
                143.26
            ],
            "iscrowd": 0,
            "attributes": {
                "occluded": false
            }
        },
        {
            "id": 58,
            "image_id": 3,
            "category_id": 22,
            "segmentation": [
                [
                    1676.47,
                    2162.1,
                    1720.17,
                    2161.9,
                    1720.17,
                    2206.4,
                    1676.37,
                    2206.5
                ]
            ],
            "area": 1958.0,
            "bbox": [
                1676.37,
                2161.9,
                43.8,
                44.6
            ],
            "iscrowd": 0,
            "attributes": {
                "occluded": false
            }
        },
        {
            "id": 59,
            "image_id": 3,
            "category_id": 22,
            "segmentation": [
                [
                    2005.24,
                    2142.96,
                    2167.93,
                    2142.64,
                    2167.79,
                    2227.1,
                    2005.17,
                    2226.94
                ]
            ],
            "area": 13692.0,
            "bbox": [
                2005.17,
                2142.64,
                162.76,
                84.46
            ],
            "iscrowd": 0,
            "attributes": {
                "occluded": false
            }
        },
        {
            "id": 60,
            "image_id": 3,
            "category_id": 22,
            "segmentation": [
                [
                    1857.34,
                    2143.4,
                    2001.92,
                    2143.0,
                    2002.37,
                    2227.0,
                    1857.73,
                    2226.69
                ]
            ],
            "area": 12117.0,
            "bbox": [
                1857.34,
                2143.0,
                145.03,
                84.0
            ],
            "iscrowd": 0,
            "attributes": {
                "occluded": false
            }
        },
        {
            "id": 61,
            "image_id": 3,
            "category_id": 2,
            "segmentation": [
                [
                    1557.1,
                    1659.8,
                    1599.35,
                    1660.01,
                    1599.52,
                    1683.56,
                    1632.22,
                    1683.56,
                    1632.22,
                    1994.67,
                    2285.79,
                    1994.67,
                    2285.96,
                    2137.86,
                    1558.0,
                    2139.89
                ]
            ],
            "area": 128876.0,
            "bbox": [
                1557.1,
                1659.8,
                728.86,
                480.09
            ],
            "iscrowd": 0,
            "attributes": {
                "occluded": false
            }
        },
        {
            "id": 62,
            "image_id": 3,
            "category_id": 3,
            "segmentation": [
                [
                    1557.47,
                    1372.33,
                    1943.73,
                    1371.93,
                    1943.28,
                    1660.18,
                    1557.1,
                    1659.8
                ]
            ],
            "area": 111312.0,
            "bbox": [
                1557.1,
                1371.93,
                386.63,
                288.25
            ],
            "iscrowd": 0,
            "attributes": {
                "occluded": false
            }
        },
        {
            "id": 63,
            "image_id": 3,
            "category_id": 22,
            "segmentation": [
                [
                    1676.45,
                    1304.67,
                    1720.84,
                    1305.01,
                    1720.67,
                    1350.09,
                    1676.45,
                    1349.75
                ]
            ],
            "area": 2025.0,
            "bbox": [
                1676.45,
                1304.67,
                44.39,
                45.42
            ],
            "iscrowd": 0,
            "attributes": {
                "occluded": false
            }
        },
        {
            "id": 64,
            "image_id": 3,
            "category_id": 14,
            "segmentation": [
                [
                    1965.87,
                    1392.11,
                    2273.42,
                    1392.45,
                    2273.42,
                    1660.35,
                    1965.87,
                    1660.86
                ]
            ],
            "area": 82506.0,
            "bbox": [
                1965.87,
                1392.11,
                307.55,
                268.75
            ],
            "iscrowd": 0,
            "attributes": {
                "occluded": false
            }
        },
        {
            "id": 65,
            "image_id": 3,
            "category_id": 17,
            "segmentation": [
                [
                    1966.88,
                    1261.09,
                    1967.49,
                    1360.93,
                    2023.61,
                    1361.34,
                    2023.41,
                    1370.89,
                    2260.1,
                    1371.3,
                    2260.1,
                    1329.41,
                    2273.72,
                    1329.41,
                    2273.52,
                    1326.77,
                    2296.9,
                    1326.97,
                    2296.9,
                    1329.41,
                    2330.66,
                    1329.82,
                    2330.66,
                    1338.77,
                    2629.36,
                    1338.36,
                    2629.36,
                    1329.41,
                    2663.12,
                    1330.02,
                    2663.32,
                    1326.36,
                    2879.88,
                    1326.57,
                    2880.28,
                    1193.79,
                    2296.7,
                    1194.4,
                    2296.5,
                    1262.31
                ]
            ],
            "area": 115045.0,
            "bbox": [
                1966.88,
                1193.79,
                913.4,
                177.51
            ],
            "iscrowd": 0,
            "attributes": {
                "occluded": false
            }
        }
    ]
}